{
  "main": {
    "id": "9b7e40fade0cebce",
    "type": "split",
    "children": [
      {
        "id": "1b25572666041ffe",
        "type": "tabs",
        "children": [
          {
            "id": "11a72ef3f72f5b6b",
            "type": "leaf",
            "state": {
              "type": "markdown",
              "state": {
                "file": "Implicit Function Theorem.md",
                "mode": "source",
                "source": false
              },
              "icon": "lucide-file",
              "title": "Implicit Function Theorem"
            }
          },
          {
            "id": "1b492499d7492c16",
            "type": "leaf",
            "state": {
              "type": "markdown",
              "state": {
                "file": "Tensor Product.md",
                "mode": "source",
                "source": false
              },
              "icon": "lucide-file",
              "title": "Tensor Product"
            }
          },
          {
            "id": "d1f8854b8350f3cd",
            "type": "leaf",
            "state": {
              "type": "markdown",
              "state": {
                "file": "Stone-Weierstrass.md",
                "mode": "source",
                "source": false
              },
              "icon": "lucide-file",
              "title": "Stone-Weierstrass"
            }
          }
        ],
        "currentTab": 2
      }
    ],
    "direction": "vertical"
  },
  "left": {
    "id": "47c31238fd8704a6",
    "type": "split",
    "children": [
      {
        "id": "1220b49f1399f35c",
        "type": "tabs",
        "children": [
          {
            "id": "541ea16c0332714b",
            "type": "leaf",
            "state": {
              "type": "file-explorer",
              "state": {
                "sortOrder": "alphabetical",
                "autoReveal": false
              },
              "icon": "lucide-folder-closed",
              "title": "Files"
            }
          },
          {
            "id": "af9380770a9a8124",
            "type": "leaf",
            "state": {
              "type": "search",
              "state": {
                "query": "",
                "matchingCase": false,
                "explainSearch": false,
                "collapseAll": false,
                "extraContext": false,
                "sortOrder": "alphabetical"
              },
              "icon": "lucide-search",
              "title": "Search"
            }
          },
          {
            "id": "86a3124b02aaaa83",
            "type": "leaf",
            "state": {
              "type": "bookmarks",
              "state": {},
              "icon": "lucide-bookmark",
              "title": "Bookmarks"
            }
          }
        ]
      }
    ],
    "direction": "horizontal",
    "width": 300,
    "collapsed": true
  },
  "right": {
    "id": "cfa3df474795fbe6",
    "type": "split",
    "children": [
      {
        "id": "3503e06f04297b0f",
        "type": "tabs",
        "children": [
          {
            "id": "7819bec0fd119490",
            "type": "leaf",
            "state": {
              "type": "backlink",
              "state": {
                "file": "Math Degree/Confidence Intervals.md",
                "collapseAll": false,
                "extraContext": false,
                "sortOrder": "alphabetical",
                "showSearch": false,
                "searchQuery": "",
                "backlinkCollapsed": false,
                "unlinkedCollapsed": true
              },
              "icon": "links-coming-in",
              "title": "Backlinks for Confidence Intervals"
            }
          },
          {
            "id": "250fb39c24856307",
            "type": "leaf",
            "state": {
              "type": "outgoing-link",
              "state": {
                "file": "Math Degree/Confidence Intervals.md",
                "linksCollapsed": false,
                "unlinkedCollapsed": true
              },
              "icon": "links-going-out",
              "title": "Outgoing links from Confidence Intervals"
            }
          },
          {
            "id": "3ebe948751713f19",
            "type": "leaf",
            "state": {
              "type": "tag",
              "state": {
                "sortOrder": "frequency",
                "useHierarchy": true
              },
              "icon": "lucide-tags",
              "title": "Tags"
            }
          },
          {
            "id": "836e00c54e3840f8",
            "type": "leaf",
            "state": {
              "type": "outline",
              "state": {
                "file": "Math Degree/Confidence Intervals.md"
              },
              "icon": "lucide-list",
              "title": "Outline of Confidence Intervals"
            }
          }
        ]
      }
    ],
    "direction": "horizontal",
    "width": 300,
    "collapsed": true
  },
  "left-ribbon": {
    "hiddenItems": {
      "switcher:Open quick switcher": false,
      "graph:Open graph view": false,
      "canvas:Create new canvas": false,
      "daily-notes:Open today's daily note": false,
      "templates:Insert template": false,
      "command-palette:Open command palette": false
    }
  },
  "active": "d1f8854b8350f3cd",
  "lastOpenFiles": [
    "Connectedness.md",
    "Stone-Weierstrass.md",
    "Quotient Space.md",
    "Tensor Product.md",
    "Implicit Function Theorem.md",
    "Singular Value Decomposition.md",
    "Generalized Eigenspace.md",
    "Inner Product Space.md",
    "Group Actions.md",
    "Well-Defined.md",
    "Kronecker Product.md",
    "Lagrange Interpolation.md",
    "Dual Space.md",
    "Evaluation Map.md",
    "Inverse Function Theorem.md",
    "Sylow Theorems.md",
    "Global Inversion Theorem.md",
    "Adjoints.md",
    "Rings.md",
    "Categories.md",
    "Real Function of Several Variables.md",
    "Jordan Form.md",
    "Jacobian.md",
    "Metric Spaces.md",
    "Schmidt Decomposition.md",
    "Function Spaces for Math 445.md",
    "Untitled.canvas",
    "Untitled 1.canvas",
    "Pasted image 20240119100450.png",
    "Minima",
    "snip.json~",
    "snip.json",
    "obsidian.snippets~",
    "obsidian.snippets",
    "convertsnip.py~",
    "convertsnip.py",
    "snip.txt"
  ]
}